themida_unmutate/__init__.py
themida_unmutate/__main__.py
themida_unmutate/logging.py
themida_unmutate/main.py
themida_unmutate/miasm_utils.py
themida_unmutate/rebuilding.py
themida_unmutate/symbolic_execution/__init__.py
themida_unmutate/symbolic_execution/x86/__init__.py
themida_unmutate/unwrapping.py
themida_unmutate-0.2.1.dist-info/LICENSE
themida_unmutate-0.2.1.dist-info/METADATA
themida_unmutate-0.2.1.dist-info/WHEEL
themida_unmutate-0.2.1.dist-info/entry_points.txt
themida_unmutate-0.2.1.dist-info/RECORD
