Metadata-Version: 2.1
Name: themida-unmutate
Version: 0.2.1
Summary: Static deobfuscator for Themida's mutation-based obfuscation.
License: GPL-3.0-or-later
Author: ergrelet
Author-email: ergrelet@users.noreply.github.com
Requires-Python: >=3.11,<4.0
Classifier: License :: OSI Approved :: GNU General Public License v3 or later (GPLv3+)
Classifier: Programming Language :: Python :: 3
Classifier: Programming Language :: Python :: 3.11
Classifier: Programming Language :: Python :: 3.12
Requires-Dist: lief (>=0.15.1,<0.16.0)
Requires-Dist: miasm (>=0.1.5,<0.2.0)
